[
  {
    "Player":"Jonathan Taylor",
    "Rush Yds":1811,
    "Att":332,
    "TD":18,
    "20+":14,
    "40+":5,
    "Lng":83,
    "Rush 1st":107,
    "Rush 1st%":3.103,
    "Rush FUM":3
  },
  {
    "Player":"Nick Chubb",
    "Rush Yds":1259,
    "Att":228,
    "TD":8,
    "20+":12,
    "40+":2,
    "Lng":70,
    "Rush 1st":61,
    "Rush 1st%":3.738,
    "Rush FUM":2
  },
  {
    "Player":"Joe Mixon",
    "Rush Yds":1205,
    "Att":292,
    "TD":13,
    "20+":6,
    "40+":0,
    "Lng":32,
    "Rush 1st":60,
    "Rush 1st%":4.867,
    "Rush FUM":1
  },
  {
    "Player":"Najee Harris",
    "Rush Yds":1200,
    "Att":307,
    "TD":7,
    "20+":6,
    "40+":0,
    "Lng":37,
    "Rush 1st":62,
    "Rush 1st%":4.952,
    "Rush FUM":0
  },
  {
    "Player":"Dalvin Cook",
    "Rush Yds":1159,
    "Att":249,
    "TD":6,
    "20+":9,
    "40+":1,
    "Lng":66,
    "Rush 1st":57,
    "Rush 1st%":4.368,
    "Rush FUM":3
  },
  {
    "Player":"Antonio Gibson",
    "Rush Yds":1037,
    "Att":258,
    "TD":7,
    "20+":4,
    "40+":0,
    "Lng":27,
    "Rush 1st":65,
    "Rush 1st%":3.969,
    "Rush FUM":5
  },
  {
    "Player":"Ezekiel Elliott",
    "Rush Yds":1002,
    "Att":237,
    "TD":10,
    "20+":3,
    "40+":1,
    "Lng":47,
    "Rush 1st":55,
    "Rush 1st%":4.309,
    "Rush FUM":1
  },
  {
    "Player":"Elijah Mitchell",
    "Rush Yds":963,
    "Att":207,
    "TD":5,
    "20+":6,
    "40+":0,
    "Lng":39,
    "Rush 1st":47,
    "Rush 1st%":4.404,
    "Rush FUM":0
  },
  {
    "Player":"Derrick Henry",
    "Rush Yds":937,
    "Att":219,
    "TD":10,
    "20+":3,
    "40+":2,
    "Lng":76,
    "Rush 1st":49,
    "Rush 1st%":4.469,
    "Rush FUM":1
  },
  {
    "Player":"Damien Harris",
    "Rush Yds":929,
    "Att":202,
    "TD":15,
    "20+":8,
    "40+":1,
    "Lng":64,
    "Rush 1st":55,
    "Rush 1st%":3.673,
    "Rush FUM":2
  },
  {
    "Player":"Melvin Gordon",
    "Rush Yds":918,
    "Att":203,
    "TD":8,
    "20+":3,
    "40+":2,
    "Lng":70,
    "Rush 1st":48,
    "Rush 1st%":4.229,
    "Rush FUM":3
  },
  {
    "Player":"Austin Ekeler",
    "Rush Yds":911,
    "Att":206,
    "TD":12,
    "20+":3,
    "40+":0,
    "Lng":28,
    "Rush 1st":53,
    "Rush 1st%":3.887,
    "Rush FUM":0
  },
  {
    "Player":"Javonte Williams",
    "Rush Yds":903,
    "Att":203,
    "TD":4,
    "20+":6,
    "40+":1,
    "Lng":49,
    "Rush 1st":52,
    "Rush 1st%":3.904,
    "Rush FUM":2
  },
  {
    "Player":"Alvin Kamara",
    "Rush Yds":898,
    "Att":240,
    "TD":4,
    "20+":3,
    "40+":0,
    "Lng":30,
    "Rush 1st":42,
    "Rush 1st%":5.714,
    "Rush FUM":0
  },
  {
    "Player":"Josh Jacobs",
    "Rush Yds":872,
    "Att":217,
    "TD":9,
    "20+":2,
    "40+":0,
    "Lng":28,
    "Rush 1st":45,
    "Rush 1st%":4.822,
    "Rush FUM":2
  },
  {
    "Player":"Devin Singletary",
    "Rush Yds":870,
    "Att":188,
    "TD":7,
    "20+":6,
    "40+":2,
    "Lng":46,
    "Rush 1st":44,
    "Rush 1st%":4.273,
    "Rush FUM":2
  },
  {
    "Player":"David Montgomery",
    "Rush Yds":849,
    "Att":225,
    "TD":7,
    "20+":5,
    "40+":1,
    "Lng":41,
    "Rush 1st":55,
    "Rush 1st%":4.091,
    "Rush FUM":1
  },
  {
    "Player":"Mark Ingram",
    "Rush Yds":848,
    "Att":252,
    "TD":3,
    "20+":3,
    "40+":0,
    "Lng":76,
    "Rush 1st":35,
    "Rush 1st%":7.2,
    "Rush FUM":1
  },
  {
    "Player":"Sony Michel",
    "Rush Yds":845,
    "Att":208,
    "TD":4,
    "20+":2,
    "40+":0,
    "Lng":39,
    "Rush 1st":49,
    "Rush 1st%":4.245,
    "Rush FUM":1
  },
  {
    "Player":"Leonard Fournette",
    "Rush Yds":812,
    "Att":180,
    "TD":8,
    "20+":5,
    "40+":1,
    "Lng":47,
    "Rush 1st":45,
    "Rush 1st%":4.0,
    "Rush FUM":0
  },
  {
    "Player":"A.J. Dillon",
    "Rush Yds":803,
    "Att":187,
    "TD":5,
    "20+":2,
    "40+":0,
    "Lng":36,
    "Rush 1st":50,
    "Rush 1st%":3.74,
    "Rush FUM":1
  },
  {
    "Player":"Aaron Jones",
    "Rush Yds":799,
    "Att":171,
    "TD":4,
    "20+":5,
    "40+":1,
    "Lng":57,
    "Rush 1st":37,
    "Rush 1st%":4.622,
    "Rush FUM":1
  },
  {
    "Player":"Jalen Hurts",
    "Rush Yds":784,
    "Att":139,
    "TD":10,
    "20+":7,
    "40+":0,
    "Lng":31,
    "Rush 1st":56,
    "Rush 1st%":2.482,
    "Rush FUM":3
  },
  {
    "Player":"James Robinson",
    "Rush Yds":767,
    "Att":164,
    "TD":8,
    "20+":4,
    "40+":1,
    "Lng":58,
    "Rush 1st":41,
    "Rush 1st%":4.0,
    "Rush FUM":2
  },
  {
    "Player":"Lamar Jackson",
    "Rush Yds":767,
    "Att":133,
    "TD":2,
    "20+":5,
    "40+":0,
    "Lng":31,
    "Rush 1st":48,
    "Rush 1st%":2.771,
    "Rush FUM":3
  },
  {
    "Player":"Josh Allen",
    "Rush Yds":763,
    "Att":122,
    "TD":6,
    "20+":9,
    "40+":0,
    "Lng":34,
    "Rush 1st":53,
    "Rush 1st%":2.302,
    "Rush FUM":5
  },
  {
    "Player":"Miles Sanders",
    "Rush Yds":754,
    "Att":137,
    "TD":0,
    "20+":7,
    "40+":0,
    "Lng":38,
    "Rush 1st":33,
    "Rush 1st%":4.152,
    "Rush FUM":1
  },
  {
    "Player":"James Conner",
    "Rush Yds":752,
    "Att":202,
    "TD":15,
    "20+":3,
    "40+":0,
    "Lng":35,
    "Rush 1st":53,
    "Rush 1st%":3.811,
    "Rush FUM":2
  },
  {
    "Player":"Rashaad Penny",
    "Rush Yds":749,
    "Att":119,
    "TD":6,
    "20+":11,
    "40+":2,
    "Lng":62,
    "Rush 1st":28,
    "Rush 1st%":4.25,
    "Rush FUM":0
  },
  {
    "Player":"Tony Pollard",
    "Rush Yds":719,
    "Att":130,
    "TD":2,
    "20+":4,
    "40+":1,
    "Lng":58,
    "Rush 1st":35,
    "Rush 1st%":3.714,
    "Rush FUM":0
  },
  {
    "Player":"Darrell Henderson",
    "Rush Yds":688,
    "Att":149,
    "TD":5,
    "20+":1,
    "40+":0,
    "Lng":29,
    "Rush 1st":39,
    "Rush 1st%":3.821,
    "Rush FUM":0
  },
  {
    "Player":"Michael Carter",
    "Rush Yds":639,
    "Att":147,
    "TD":4,
    "20+":3,
    "40+":1,
    "Lng":55,
    "Rush 1st":29,
    "Rush 1st%":5.069,
    "Rush FUM":0
  },
  {
    "Player":"Cordarrelle Patterson",
    "Rush Yds":618,
    "Att":153,
    "TD":6,
    "20+":2,
    "40+":0,
    "Lng":39,
    "Rush 1st":29,
    "Rush 1st%":5.276,
    "Rush FUM":1
  },
  {
    "Player":"D'Andre Swift",
    "Rush Yds":617,
    "Att":151,
    "TD":5,
    "20+":3,
    "40+":1,
    "Lng":57,
    "Rush 1st":28,
    "Rush 1st%":5.393,
    "Rush FUM":0
  },
  {
    "Player":"Chuba Hubbard",
    "Rush Yds":612,
    "Att":172,
    "TD":5,
    "20+":3,
    "40+":0,
    "Lng":26,
    "Rush 1st":36,
    "Rush 1st%":4.778,
    "Rush FUM":1
  },
  {
    "Player":"Myles Gaskin",
    "Rush Yds":612,
    "Att":173,
    "TD":3,
    "20+":2,
    "40+":0,
    "Lng":30,
    "Rush 1st":25,
    "Rush 1st%":6.92,
    "Rush FUM":2
  },
  {
    "Player":"Rhamondre Stevenson",
    "Rush Yds":606,
    "Att":133,
    "TD":5,
    "20+":1,
    "40+":0,
    "Lng":21,
    "Rush 1st":33,
    "Rush 1st%":4.03,
    "Rush FUM":1
  },
  {
    "Player":"Jamaal Williams",
    "Rush Yds":601,
    "Att":153,
    "TD":3,
    "20+":1,
    "40+":0,
    "Lng":20,
    "Rush 1st":42,
    "Rush 1st%":3.643,
    "Rush FUM":1
  },
  {
    "Player":"Devontae Booker",
    "Rush Yds":593,
    "Att":145,
    "TD":2,
    "20+":3,
    "40+":0,
    "Lng":31,
    "Rush 1st":31,
    "Rush 1st%":4.677,
    "Rush FUM":0
  },
  {
    "Player":"Saquon Barkley",
    "Rush Yds":593,
    "Att":162,
    "TD":2,
    "20+":3,
    "40+":1,
    "Lng":41,
    "Rush 1st":27,
    "Rush 1st%":6.0,
    "Rush FUM":1
  },
  {
    "Player":"Chase Edmonds",
    "Rush Yds":592,
    "Att":116,
    "TD":2,
    "20+":3,
    "40+":2,
    "Lng":54,
    "Rush 1st":32,
    "Rush 1st%":3.625,
    "Rush FUM":0
  },
  {
    "Player":"Devonta Freeman",
    "Rush Yds":576,
    "Att":133,
    "TD":5,
    "20+":4,
    "40+":0,
    "Lng":32,
    "Rush 1st":31,
    "Rush 1st%":4.29,
    "Rush FUM":0
  },
  {
    "Player":"D'Onta Foreman",
    "Rush Yds":566,
    "Att":133,
    "TD":3,
    "20+":4,
    "40+":0,
    "Lng":35,
    "Rush 1st":22,
    "Rush 1st%":6.045,
    "Rush FUM":2
  },
  {
    "Player":"Darrel Williams",
    "Rush Yds":558,
    "Att":144,
    "TD":6,
    "20+":1,
    "40+":0,
    "Lng":21,
    "Rush 1st":40,
    "Rush 1st%":3.6,
    "Rush FUM":0
  },
  {
    "Player":"D'Ernest Johnson",
    "Rush Yds":534,
    "Att":100,
    "TD":3,
    "20+":4,
    "40+":0,
    "Lng":30,
    "Rush 1st":24,
    "Rush 1st%":4.167,
    "Rush FUM":0
  },
  {
    "Player":"Clyde Edwards-Helaire",
    "Rush Yds":517,
    "Att":119,
    "TD":4,
    "20+":0,
    "40+":0,
    "Lng":17,
    "Rush 1st":21,
    "Rush 1st%":5.667,
    "Rush FUM":2
  },
  {
    "Player":"Mike Davis",
    "Rush Yds":503,
    "Att":138,
    "TD":3,
    "20+":0,
    "40+":0,
    "Lng":18,
    "Rush 1st":21,
    "Rush 1st%":6.571,
    "Rush FUM":2
  },
  {
    "Player":"Latavius Murray",
    "Rush Yds":501,
    "Att":119,
    "TD":6,
    "20+":3,
    "40+":1,
    "Lng":46,
    "Rush 1st":36,
    "Rush 1st%":3.306,
    "Rush FUM":0
  },
  {
    "Player":"Alexander Mattison",
    "Rush Yds":491,
    "Att":134,
    "TD":3,
    "20+":2,
    "40+":1,
    "Lng":48,
    "Rush 1st":28,
    "Rush 1st%":4.786,
    "Rush FUM":1
  },
  {
    "Player":"Christian McCaffrey",
    "Rush Yds":442,
    "Att":99,
    "TD":1,
    "20+":0,
    "40+":0,
    "Lng":18,
    "Rush 1st":19,
    "Rush 1st%":5.211,
    "Rush FUM":1
  },
  {
    "Player":"Khalil Herbert",
    "Rush Yds":433,
    "Att":103,
    "TD":2,
    "20+":4,
    "40+":0,
    "Lng":29,
    "Rush 1st":24,
    "Rush 1st%":4.292,
    "Rush FUM":0
  },
  {
    "Player":"Ronald Jones",
    "Rush Yds":428,
    "Att":101,
    "TD":4,
    "20+":1,
    "40+":0,
    "Lng":30,
    "Rush 1st":25,
    "Rush 1st%":4.04,
    "Rush FUM":2
  },
  {
    "Player":"Rex Burkhead",
    "Rush Yds":427,
    "Att":122,
    "TD":3,
    "20+":2,
    "40+":0,
    "Lng":36,
    "Rush 1st":30,
    "Rush 1st%":4.067,
    "Rush FUM":1
  },
  {
    "Player":"Kyler Murray",
    "Rush Yds":423,
    "Att":88,
    "TD":5,
    "20+":1,
    "40+":1,
    "Lng":57,
    "Rush 1st":25,
    "Rush 1st%":3.52,
    "Rush FUM":10
  },
  {
    "Player":"Justin Fields",
    "Rush Yds":420,
    "Att":72,
    "TD":2,
    "20+":3,
    "40+":0,
    "Lng":23,
    "Rush 1st":22,
    "Rush 1st%":3.273,
    "Rush FUM":4
  },
  {
    "Player":"Alex Collins",
    "Rush Yds":411,
    "Att":108,
    "TD":2,
    "20+":2,
    "40+":0,
    "Lng":25,
    "Rush 1st":22,
    "Rush 1st%":4.909,
    "Rush FUM":0
  },
  {
    "Player":"Jordan Howard",
    "Rush Yds":406,
    "Att":86,
    "TD":3,
    "20+":1,
    "40+":0,
    "Lng":25,
    "Rush 1st":24,
    "Rush 1st%":3.583,
    "Rush FUM":0
  },
  {
    "Player":"Kareem Hunt",
    "Rush Yds":386,
    "Att":78,
    "TD":5,
    "20+":2,
    "40+":0,
    "Lng":33,
    "Rush 1st":22,
    "Rush 1st%":3.545,
    "Rush FUM":0
  },
  {
    "Player":"Patrick Mahomes",
    "Rush Yds":381,
    "Att":66,
    "TD":2,
    "20+":4,
    "40+":0,
    "Lng":32,
    "Rush 1st":25,
    "Rush 1st%":2.64,
    "Rush FUM":3
  },
  {
    "Player":"Taysom Hill",
    "Rush Yds":374,
    "Att":70,
    "TD":5,
    "20+":3,
    "40+":1,
    "Lng":44,
    "Rush 1st":26,
    "Rush 1st%":2.692,
    "Rush FUM":1
  },
  {
    "Player":"Boston Scott",
    "Rush Yds":373,
    "Att":87,
    "TD":7,
    "20+":2,
    "40+":0,
    "Lng":23,
    "Rush 1st":24,
    "Rush 1st%":3.625,
    "Rush FUM":1
  },
  {
    "Player":"Deebo Samuel",
    "Rush Yds":365,
    "Att":59,
    "TD":8,
    "20+":5,
    "40+":1,
    "Lng":49,
    "Rush 1st":21,
    "Rush 1st%":2.81,
    "Rush FUM":0
  },
  {
    "Player":"Justin Jackson",
    "Rush Yds":364,
    "Att":68,
    "TD":2,
    "20+":2,
    "40+":1,
    "Lng":75,
    "Rush 1st":18,
    "Rush 1st%":3.778,
    "Rush FUM":1
  },
  {
    "Player":"Tevin Coleman",
    "Rush Yds":356,
    "Att":84,
    "TD":0,
    "20+":1,
    "40+":0,
    "Lng":20,
    "Rush 1st":19,
    "Rush 1st%":4.421,
    "Rush FUM":0
  },
  {
    "Player":"Dontrell Hilliard",
    "Rush Yds":350,
    "Att":56,
    "TD":2,
    "20+":2,
    "40+":1,
    "Lng":68,
    "Rush 1st":15,
    "Rush 1st%":3.733,
    "Rush FUM":1
  },
  {
    "Player":"Zack Moss",
    "Rush Yds":345,
    "Att":96,
    "TD":4,
    "20+":0,
    "40+":0,
    "Lng":17,
    "Rush 1st":22,
    "Rush 1st%":4.364,
    "Rush FUM":0
  },
  {
    "Player":"Trevor Lawrence",
    "Rush Yds":334,
    "Att":73,
    "TD":2,
    "20+":1,
    "40+":0,
    "Lng":26,
    "Rush 1st":21,
    "Rush 1st%":3.476,
    "Rush FUM":2
  },
  {
    "Player":"Duke Johnson",
    "Rush Yds":330,
    "Att":71,
    "TD":3,
    "20+":1,
    "40+":0,
    "Lng":27,
    "Rush 1st":18,
    "Rush 1st%":3.944,
    "Rush FUM":0
  },
  {
    "Player":"Taylor Heinicke",
    "Rush Yds":313,
    "Att":60,
    "TD":1,
    "20+":2,
    "40+":0,
    "Lng":38,
    "Rush 1st":20,
    "Rush 1st%":3.0,
    "Rush FUM":3
  },
  {
    "Player":"Justin Herbert",
    "Rush Yds":302,
    "Att":63,
    "TD":3,
    "20+":1,
    "40+":0,
    "Lng":36,
    "Rush 1st":28,
    "Rush 1st%":2.25,
    "Rush FUM":0
  },
  {
    "Player":"Daniel Jones",
    "Rush Yds":298,
    "Att":62,
    "TD":2,
    "20+":2,
    "40+":1,
    "Lng":46,
    "Rush 1st":16,
    "Rush 1st%":3.875,
    "Rush FUM":2
  },
  {
    "Player":"Jeff Wilson",
    "Rush Yds":294,
    "Att":79,
    "TD":2,
    "20+":0,
    "40+":0,
    "Lng":17,
    "Rush 1st":19,
    "Rush 1st%":4.158,
    "Rush FUM":1
  },
  {
    "Player":"Tyler Huntley",
    "Rush Yds":294,
    "Att":47,
    "TD":2,
    "20+":1,
    "40+":0,
    "Lng":21,
    "Rush 1st":22,
    "Rush 1st%":2.136,
    "Rush FUM":1
  },
  {
    "Player":"Kenneth Gainwell",
    "Rush Yds":291,
    "Att":68,
    "TD":5,
    "20+":0,
    "40+":0,
    "Lng":18,
    "Rush 1st":19,
    "Rush 1st%":3.579,
    "Rush FUM":1
  },
  {
    "Player":"Nyheim Hines",
    "Rush Yds":276,
    "Att":56,
    "TD":2,
    "20+":2,
    "40+":0,
    "Lng":34,
    "Rush 1st":15,
    "Rush 1st%":3.733,
    "Rush FUM":0
  },
  {
    "Player":"Ryan Tannehill",
    "Rush Yds":270,
    "Att":55,
    "TD":7,
    "20+":2,
    "40+":0,
    "Lng":28,
    "Rush 1st":32,
    "Rush 1st%":1.719,
    "Rush FUM":4
  },
  {
    "Player":"Jaret Patterson",
    "Rush Yds":266,
    "Att":68,
    "TD":2,
    "20+":0,
    "40+":0,
    "Lng":13,
    "Rush 1st":15,
    "Rush 1st%":4.533,
    "Rush FUM":1
  },
  {
    "Player":"Derrick Gore",
    "Rush Yds":256,
    "Att":51,
    "TD":2,
    "20+":2,
    "40+":1,
    "Lng":51,
    "Rush 1st":12,
    "Rush 1st%":4.25,
    "Rush FUM":0
  },
  {
    "Player":"Kenyan Drake",
    "Rush Yds":254,
    "Att":62,
    "TD":2,
    "20+":1,
    "40+":0,
    "Lng":21,
    "Rush 1st":15,
    "Rush 1st%":4.133,
    "Rush FUM":0
  },
  {
    "Player":"Carlos Hyde",
    "Rush Yds":253,
    "Att":72,
    "TD":1,
    "20+":0,
    "40+":0,
    "Lng":18,
    "Rush 1st":14,
    "Rush 1st%":5.143,
    "Rush FUM":2
  },
  {
    "Player":"Phillip Lindsay",
    "Rush Yds":249,
    "Att":88,
    "TD":1,
    "20+":1,
    "40+":0,
    "Lng":44,
    "Rush 1st":11,
    "Rush 1st%":8.0,
    "Rush FUM":0
  },
  {
    "Player":"Samaje Perine",
    "Rush Yds":246,
    "Att":55,
    "TD":1,
    "20+":2,
    "40+":1,
    "Lng":46,
    "Rush 1st":11,
    "Rush 1st%":5.0,
    "Rush FUM":0
  },
  {
    "Player":"Royce Freeman",
    "Rush Yds":246,
    "Att":77,
    "TD":0,
    "20+":0,
    "40+":0,
    "Lng":39,
    "Rush 1st":12,
    "Rush 1st%":6.417,
    "Rush FUM":0
  },
  {
    "Player":"Ty Johnson",
    "Rush Yds":238,
    "Att":61,
    "TD":2,
    "20+":2,
    "40+":0,
    "Lng":24,
    "Rush 1st":13,
    "Rush 1st%":4.692,
    "Rush FUM":1
  },
  {
    "Player":"Chris Carson",
    "Rush Yds":232,
    "Att":54,
    "TD":3,
    "20+":2,
    "40+":0,
    "Lng":33,
    "Rush 1st":11,
    "Rush 1st%":4.909,
    "Rush FUM":1
  },
  {
    "Player":"Craig Reynolds",
    "Rush Yds":230,
    "Att":55,
    "TD":0,
    "20+":2,
    "40+":0,
    "Lng":35,
    "Rush 1st":11,
    "Rush 1st%":5.0,
    "Rush FUM":0
  },
  {
    "Player":"Cam Newton",
    "Rush Yds":230,
    "Att":47,
    "TD":5,
    "20+":2,
    "40+":0,
    "Lng":33,
    "Rush 1st":19,
    "Rush 1st%":2.474,
    "Rush FUM":4
  },
  {
    "Player":"David Johnson",
    "Rush Yds":228,
    "Att":67,
    "TD":0,
    "20+":0,
    "40+":0,
    "Lng":15,
    "Rush 1st":7,
    "Rush 1st%":9.571,
    "Rush FUM":1
  },
  {
    "Player":"Brandon Bolden",
    "Rush Yds":226,
    "Att":44,
    "TD":1,
    "20+":2,
    "40+":0,
    "Lng":24,
    "Rush 1st":12,
    "Rush 1st%":3.667,
    "Rush FUM":1
  },
  {
    "Player":"Sam Darnold",
    "Rush Yds":222,
    "Att":48,
    "TD":5,
    "20+":2,
    "40+":0,
    "Lng":30,
    "Rush 1st":21,
    "Rush 1st%":2.286,
    "Rush FUM":2
  },
  {
    "Player":"Carson Wentz",
    "Rush Yds":215,
    "Att":57,
    "TD":1,
    "20+":0,
    "40+":0,
    "Lng":18,
    "Rush 1st":21,
    "Rush 1st%":2.714,
    "Rush FUM":4
  },
  {
    "Player":"J.D. McKissic",
    "Rush Yds":212,
    "Att":48,
    "TD":2,
    "20+":0,
    "40+":0,
    "Lng":15,
    "Rush 1st":14,
    "Rush 1st%":3.429,
    "Rush FUM":0
  },
  {
    "Player":"Peyton Barber",
    "Rush Yds":212,
    "Att":55,
    "TD":2,
    "20+":1,
    "40+":0,
    "Lng":27,
    "Rush 1st":12,
    "Rush 1st%":4.583,
    "Rush FUM":1
  },
  {
    "Player":"Wayne Gallman",
    "Rush Yds":208,
    "Att":56,
    "TD":0,
    "20+":0,
    "40+":0,
    "Lng":34,
    "Rush 1st":10,
    "Rush 1st%":5.6,
    "Rush FUM":0
  },
  {
    "Player":"Ameer Abdullah",
    "Rush Yds":196,
    "Att":58,
    "TD":0,
    "20+":0,
    "40+":0,
    "Lng":33,
    "Rush 1st":8,
    "Rush 1st%":7.25,
    "Rush FUM":0
  },
  {
    "Player":"Zach Wilson",
    "Rush Yds":185,
    "Att":29,
    "TD":4,
    "20+":3,
    "40+":1,
    "Lng":52,
    "Rush 1st":10,
    "Rush 1st%":2.9,
    "Rush FUM":0
  },
  {
    "Player":"Ty'Son Williams",
    "Rush Yds":185,
    "Att":35,
    "TD":1,
    "20+":2,
    "40+":0,
    "Lng":35,
    "Rush 1st":7,
    "Rush 1st%":5.0,
    "Rush FUM":1
  },
  {
    "Player":"Le'Veon Bell",
    "Rush Yds":184,
    "Att":70,
    "TD":4,
    "20+":0,
    "40+":0,
    "Lng":31,
    "Rush 1st":17,
    "Rush 1st%":4.118,
    "Rush FUM":0
  },
  {
    "Player":"Russell Wilson",
    "Rush Yds":183,
    "Att":43,
    "TD":2,
    "20+":0,
    "40+":0,
    "Lng":17,
    "Rush 1st":17,
    "Rush 1st%":2.529,
    "Rush FUM":2
  },
  {
    "Player":"Ke'Shawn Vaughn",
    "Rush Yds":180,
    "Att":36,
    "TD":2,
    "20+":1,
    "40+":1,
    "Lng":55,
    "Rush 1st":9,
    "Rush 1st%":4.0,
    "Rush FUM":0
  },
  {
    "Player":"Travis Homer",
    "Rush Yds":177,
    "Att":21,
    "TD":1,
    "20+":2,
    "40+":1,
    "Lng":73,
    "Rush 1st":7,
    "Rush 1st%":3.0,
    "Rush FUM":0
  },
  {
    "Player":"Trey Lance",
    "Rush Yds":168,
    "Att":38,
    "TD":1,
    "20+":0,
    "40+":0,
    "Lng":15,
    "Rush 1st":8,
    "Rush 1st%":4.75,
    "Rush FUM":0
  },
  {
    "Player":"Trey Sermon",
    "Rush Yds":167,
    "Att":41,
    "TD":1,
    "20+":0,
    "40+":0,
    "Lng":16,
    "Rush 1st":9,
    "Rush 1st%":4.556,
    "Rush FUM":0
  },
  {
    "Player":"Jameis Winston",
    "Rush Yds":166,
    "Att":32,
    "TD":1,
    "20+":1,
    "40+":0,
    "Lng":20,
    "Rush 1st":17,
    "Rush 1st%":1.882,
    "Rush FUM":0
  },
  {
    "Player":"Damien Williams",
    "Rush Yds":164,
    "Att":40,
    "TD":2,
    "20+":1,
    "40+":0,
    "Lng":23,
    "Rush 1st":11,
    "Rush 1st%":3.636,
    "Rush FUM":0
  },
  {
    "Player":"Jeremy McNichols",
    "Rush Yds":156,
    "Att":41,
    "TD":0,
    "20+":0,
    "40+":0,
    "Lng":14,
    "Rush 1st":6,
    "Rush 1st%":6.833,
    "Rush FUM":0
  },
  {
    "Player":"Tyrod Taylor",
    "Rush Yds":151,
    "Att":19,
    "TD":3,
    "20+":2,
    "40+":0,
    "Lng":30,
    "Rush 1st":7,
    "Rush 1st%":2.714,
    "Rush FUM":3
  },
  {
    "Player":"Salvon Ahmed",
    "Rush Yds":149,
    "Att":54,
    "TD":0,
    "20+":0,
    "40+":0,
    "Lng":16,
    "Rush 1st":8,
    "Rush 1st%":6.75,
    "Rush FUM":0
  },
  {
    "Player":"Dak Prescott",
    "Rush Yds":146,
    "Att":48,
    "TD":1,
    "20+":1,
    "40+":0,
    "Lng":21,
    "Rush 1st":7,
    "Rush 1st%":6.857,
    "Rush FUM":7
  },
  {
    "Player":"Tony Jones",
    "Rush Yds":142,
    "Att":54,
    "TD":0,
    "20+":0,
    "40+":0,
    "Lng":11,
    "Rush 1st":7,
    "Rush 1st%":7.714,
    "Rush FUM":0
  },
  {
    "Player":"Corey Clement",
    "Rush Yds":140,
    "Att":33,
    "TD":0,
    "20+":1,
    "40+":0,
    "Lng":38,
    "Rush 1st":7,
    "Rush 1st%":4.714,
    "Rush FUM":0
  },
  {
    "Player":"DeeJay Dallas",
    "Rush Yds":138,
    "Att":33,
    "TD":2,
    "20+":0,
    "40+":0,
    "Lng":15,
    "Rush 1st":10,
    "Rush 1st%":3.3,
    "Rush FUM":0
  },
  {
    "Player":"Dare Ogunbowale",
    "Rush Yds":137,
    "Att":43,
    "TD":1,
    "20+":0,
    "40+":0,
    "Lng":12,
    "Rush 1st":5,
    "Rush 1st%":8.6,
    "Rush FUM":0
  },
  {
    "Player":"Baker Mayfield",
    "Rush Yds":134,
    "Att":37,
    "TD":1,
    "20+":0,
    "40+":0,
    "Lng":14,
    "Rush 1st":12,
    "Rush 1st%":3.083,
    "Rush FUM":1
  },
  {
    "Player":"Mac Jones",
    "Rush Yds":129,
    "Att":44,
    "TD":0,
    "20+":0,
    "40+":0,
    "Lng":13,
    "Rush 1st":22,
    "Rush 1st%":2.0,
    "Rush FUM":3
  },
  {
    "Player":"Tua Tagovailoa",
    "Rush Yds":128,
    "Att":42,
    "TD":3,
    "20+":1,
    "40+":0,
    "Lng":23,
    "Rush 1st":13,
    "Rush 1st%":3.231,
    "Rush FUM":2
  },
  {
    "Player":"Malcolm Brown",
    "Rush Yds":125,
    "Att":33,
    "TD":1,
    "20+":1,
    "40+":0,
    "Lng":24,
    "Rush 1st":6,
    "Rush 1st%":5.5,
    "Rush FUM":0
  },
  {
    "Player":"Matt Breida",
    "Rush Yds":125,
    "Att":26,
    "TD":1,
    "20+":1,
    "40+":0,
    "Lng":28,
    "Rush 1st":5,
    "Rush 1st%":5.2,
    "Rush FUM":1
  },
  {
    "Player":"Kendrick Bourne",
    "Rush Yds":125,
    "Att":12,
    "TD":0,
    "20+":0,
    "40+":0,
    "Lng":18,
    "Rush 1st":7,
    "Rush 1st%":1.714,
    "Rush FUM":0
  },
  {
    "Player":"Godwin Igwebuike",
    "Rush Yds":118,
    "Att":16,
    "TD":1,
    "20+":1,
    "40+":1,
    "Lng":42,
    "Rush 1st":7,
    "Rush 1st%":2.286,
    "Rush FUM":1
  },
  {
    "Player":"Joe Burrow",
    "Rush Yds":118,
    "Att":40,
    "TD":2,
    "20+":0,
    "40+":0,
    "Lng":12,
    "Rush 1st":14,
    "Rush 1st%":2.857,
    "Rush FUM":1
  },
  {
    "Player":"Eno Benjamin",
    "Rush Yds":118,
    "Att":34,
    "TD":1,
    "20+":1,
    "40+":0,
    "Lng":21,
    "Rush 1st":4,
    "Rush 1st%":8.5,
    "Rush FUM":0
  },
  {
    "Player":"Kirk Cousins",
    "Rush Yds":115,
    "Att":29,
    "TD":1,
    "20+":1,
    "40+":0,
    "Lng":29,
    "Rush 1st":8,
    "Rush 1st%":3.625,
    "Rush FUM":2
  },
  {
    "Player":"Jamal Agnew",
    "Rush Yds":111,
    "Att":7,
    "TD":1,
    "20+":1,
    "40+":1,
    "Lng":66,
    "Rush 1st":3,
    "Rush 1st%":2.333,
    "Rush FUM":0
  },
  {
    "Player":"Derek Carr",
    "Rush Yds":108,
    "Att":40,
    "TD":0,
    "20+":1,
    "40+":0,
    "Lng":22,
    "Rush 1st":9,
    "Rush 1st%":4.444,
    "Rush FUM":4
  },
  {
    "Player":"Teddy Bridgewater",
    "Rush Yds":106,
    "Att":30,
    "TD":2,
    "20+":0,
    "40+":0,
    "Lng":13,
    "Rush 1st":16,
    "Rush 1st%":1.875,
    "Rush FUM":1
  },
  {
    "Player":"Qadree Ollison",
    "Rush Yds":105,
    "Att":21,
    "TD":1,
    "20+":0,
    "40+":0,
    "Lng":19,
    "Rush 1st":7,
    "Rush 1st%":3.0,
    "Rush FUM":1
  },
  {
    "Player":"Joshua Kelley",
    "Rush Yds":102,
    "Att":33,
    "TD":0,
    "20+":0,
    "40+":0,
    "Lng":14,
    "Rush 1st":5,
    "Rush 1st%":6.6,
    "Rush FUM":1
  },
  {
    "Player":"Austin Walter",
    "Rush Yds":101,
    "Att":26,
    "TD":1,
    "20+":0,
    "40+":0,
    "Lng":14,
    "Rush 1st":5,
    "Rush 1st%":5.2,
    "Rush FUM":0
  },
  {
    "Player":"Aaron Rodgers",
    "Rush Yds":101,
    "Att":33,
    "TD":3,
    "20+":0,
    "40+":0,
    "Lng":18,
    "Rush 1st":10,
    "Rush 1st%":3.3,
    "Rush FUM":2
  },
  {
    "Player":"Marlon Mack",
    "Rush Yds":101,
    "Att":28,
    "TD":0,
    "20+":1,
    "40+":0,
    "Lng":22,
    "Rush 1st":6,
    "Rush 1st%":4.667,
    "Rush FUM":0
  },
  {
    "Player":"Elijhaa Penny",
    "Rush Yds":99,
    "Att":24,
    "TD":1,
    "20+":0,
    "40+":0,
    "Lng":12,
    "Rush 1st":9,
    "Rush 1st%":2.667,
    "Rush FUM":0
  },
  {
    "Player":"Benny Snell",
    "Rush Yds":98,
    "Att":36,
    "TD":0,
    "20+":0,
    "40+":0,
    "Lng":9,
    "Rush 1st":2,
    "Rush 1st%":18.0,
    "Rush FUM":0
  },
  {
    "Player":"Adrian Peterson",
    "Rush Yds":98,
    "Att":38,
    "TD":2,
    "20+":0,
    "40+":0,
    "Lng":23,
    "Rush 1st":6,
    "Rush 1st%":6.333,
    "Rush FUM":1
  },
  {
    "Player":"Tyreek Hill",
    "Rush Yds":96,
    "Att":9,
    "TD":0,
    "20+":1,
    "40+":0,
    "Lng":33,
    "Rush 1st":4,
    "Rush 1st%":2.25,
    "Rush FUM":0
  },
  {
    "Player":"Chase Claypool",
    "Rush Yds":96,
    "Att":14,
    "TD":0,
    "20+":1,
    "40+":0,
    "Lng":25,
    "Rush 1st":7,
    "Rush 1st%":2.0,
    "Rush FUM":0
  },
  {
    "Player":"Patrick Taylor",
    "Rush Yds":89,
    "Att":23,
    "TD":1,
    "20+":0,
    "40+":0,
    "Lng":12,
    "Rush 1st":5,
    "Rush 1st%":4.6,
    "Rush FUM":0
  },
  {
    "Player":"DeAndre Carter",
    "Rush Yds":89,
    "Att":10,
    "TD":0,
    "20+":1,
    "40+":0,
    "Lng":27,
    "Rush 1st":4,
    "Rush 1st%":2.5,
    "Rush FUM":1
  },
  {
    "Player":"Larry Rountree III",
    "Rush Yds":87,
    "Att":36,
    "TD":1,
    "20+":0,
    "40+":0,
    "Lng":13,
    "Rush 1st":5,
    "Rush 1st%":7.2,
    "Rush FUM":0
  },
  {
    "Player":"Marcus Mariota",
    "Rush Yds":87,
    "Att":13,
    "TD":1,
    "20+":1,
    "40+":0,
    "Lng":31,
    "Rush 1st":6,
    "Rush 1st%":2.167,
    "Rush FUM":1
  },
  {
    "Player":"Jared Goff",
    "Rush Yds":87,
    "Att":17,
    "TD":0,
    "20+":1,
    "40+":0,
    "Lng":26,
    "Rush 1st":4,
    "Rush 1st%":4.25,
    "Rush FUM":3
  },
  {
    "Player":"Matt Ryan",
    "Rush Yds":82,
    "Att":40,
    "TD":1,
    "20+":0,
    "40+":0,
    "Lng":17,
    "Rush 1st":9,
    "Rush 1st%":4.444,
    "Rush FUM":5
  },
  {
    "Player":"Tom Brady",
    "Rush Yds":81,
    "Att":28,
    "TD":2,
    "20+":0,
    "40+":0,
    "Lng":13,
    "Rush 1st":14,
    "Rush 1st%":2.0,
    "Rush FUM":1
  },
  {
    "Player":"Ryquell Armstead",
    "Rush Yds":80,
    "Att":15,
    "TD":0,
    "20+":1,
    "40+":0,
    "Lng":26,
    "Rush 1st":3,
    "Rush 1st%":5.0,
    "Rush FUM":0
  },
  {
    "Player":"Jonathan Williams",
    "Rush Yds":79,
    "Att":17,
    "TD":1,
    "20+":1,
    "40+":0,
    "Lng":23,
    "Rush 1st":7,
    "Rush 1st%":2.429,
    "Rush FUM":0
  },
  {
    "Player":"Chris Evans",
    "Rush Yds":77,
    "Att":17,
    "TD":0,
    "20+":0,
    "40+":0,
    "Lng":13,
    "Rush 1st":3,
    "Rush 1st%":5.667,
    "Rush FUM":0
  },
  {
    "Player":"Rondale Moore",
    "Rush Yds":76,
    "Att":18,
    "TD":0,
    "20+":1,
    "40+":0,
    "Lng":26,
    "Rush 1st":2,
    "Rush 1st%":9.0,
    "Rush FUM":0
  },
  {
    "Player":"CeeDee Lamb",
    "Rush Yds":76,
    "Att":9,
    "TD":0,
    "20+":1,
    "40+":0,
    "Lng":33,
    "Rush 1st":4,
    "Rush 1st%":2.25,
    "Rush FUM":0
  },
  {
    "Player":"Andy Dalton",
    "Rush Yds":76,
    "Att":16,
    "TD":0,
    "20+":0,
    "40+":0,
    "Lng":14,
    "Rush 1st":2,
    "Rush 1st%":8.0,
    "Rush FUM":0
  },
  {
    "Player":"Jermar Jefferson",
    "Rush Yds":74,
    "Att":15,
    "TD":2,
    "20+":1,
    "40+":0,
    "Lng":28,
    "Rush 1st":4,
    "Rush 1st%":3.75,
    "Rush FUM":0
  },
  {
    "Player":"Jacoby Brissett",
    "Rush Yds":70,
    "Att":19,
    "TD":1,
    "20+":0,
    "40+":0,
    "Lng":19,
    "Rush 1st":9,
    "Rush 1st%":2.111,
    "Rush FUM":0
  },
  {
    "Player":"JaMycal Hasty",
    "Rush Yds":68,
    "Att":16,
    "TD":1,
    "20+":1,
    "40+":0,
    "Lng":21,
    "Rush 1st":6,
    "Rush 1st%":2.667,
    "Rush FUM":0
  },
  {
    "Player":"Jake Fromm",
    "Rush Yds":65,
    "Att":8,
    "TD":0,
    "20+":1,
    "40+":0,
    "Lng":27,
    "Rush 1st":4,
    "Rush 1st%":2.0,
    "Rush FUM":0
  },
  {
    "Player":"Jerick McKinnon",
    "Rush Yds":62,
    "Att":12,
    "TD":0,
    "20+":0,
    "40+":0,
    "Lng":18,
    "Rush 1st":2,
    "Rush 1st%":6.0,
    "Rush FUM":0
  },
  {
    "Player":"Amon-Ra St. Brown",
    "Rush Yds":61,
    "Att":7,
    "TD":1,
    "20+":1,
    "40+":0,
    "Lng":26,
    "Rush 1st":2,
    "Rush 1st%":3.5,
    "Rush FUM":0
  },
  {
    "Player":"Kene Nwangwu",
    "Rush Yds":61,
    "Att":13,
    "TD":0,
    "20+":0,
    "40+":0,
    "Lng":19,
    "Rush 1st":3,
    "Rush 1st%":4.333,
    "Rush FUM":0
  },
  {
    "Player":"D'Wayne Eskridge",
    "Rush Yds":59,
    "Att":4,
    "TD":0,
    "20+":1,
    "40+":0,
    "Lng":30,
    "Rush 1st":2,
    "Rush 1st%":2.0,
    "Rush FUM":0
  },
  {
    "Player":"Giovani Bernard",
    "Rush Yds":58,
    "Att":8,
    "TD":0,
    "20+":1,
    "40+":0,
    "Lng":24,
    "Rush 1st":3,
    "Rush 1st%":2.667,
    "Rush FUM":0
  },
  {
    "Player":"Elijah Moore",
    "Rush Yds":54,
    "Att":5,
    "TD":1,
    "20+":0,
    "40+":0,
    "Lng":19,
    "Rush 1st":3,
    "Rush 1st%":1.667,
    "Rush FUM":0
  },
  {
    "Player":"Mason Rudolph",
    "Rush Yds":53,
    "Att":5,
    "TD":0,
    "20+":1,
    "40+":0,
    "Lng":26,
    "Rush 1st":3,
    "Rush 1st%":1.667,
    "Rush FUM":0
  },
  {
    "Player":"Drew Lock",
    "Rush Yds":53,
    "Att":10,
    "TD":2,
    "20+":1,
    "40+":0,
    "Lng":23,
    "Rush 1st":5,
    "Rush 1st%":2.0,
    "Rush FUM":1
  },
  {
    "Player":"Diontae Johnson",
    "Rush Yds":53,
    "Att":5,
    "TD":0,
    "20+":1,
    "40+":0,
    "Lng":25,
    "Rush 1st":2,
    "Rush 1st%":2.5,
    "Rush FUM":0
  },
  {
    "Player":"Trayveon Williams",
    "Rush Yds":51,
    "Att":15,
    "TD":0,
    "20+":0,
    "40+":0,
    "Lng":10,
    "Rush 1st":4,
    "Rush 1st%":3.75,
    "Rush FUM":0
  },
  {
    "Player":"Jason Huntley",
    "Rush Yds":51,
    "Att":13,
    "TD":0,
    "20+":0,
    "40+":0,
    "Lng":18,
    "Rush 1st":2,
    "Rush 1st%":6.5,
    "Rush FUM":0
  },
  {
    "Player":"Jimmy Garoppolo",
    "Rush Yds":51,
    "Att":38,
    "TD":3,
    "20+":0,
    "40+":0,
    "Lng":7,
    "Rush 1st":15,
    "Rush 1st%":2.533,
    "Rush FUM":4
  },
  {
    "Player":"Devin Duvernay",
    "Rush Yds":50,
    "Att":7,
    "TD":0,
    "20+":0,
    "40+":0,
    "Lng":19,
    "Rush 1st":3,
    "Rush 1st%":2.333,
    "Rush FUM":0
  },
  {
    "Player":"D.J. Moore",
    "Rush Yds":48,
    "Att":8,
    "TD":0,
    "20+":0,
    "40+":0,
    "Lng":14,
    "Rush 1st":4,
    "Rush 1st%":2.0,
    "Rush FUM":0
  },
  {
    "Player":"Isaiah McKenzie",
    "Rush Yds":47,
    "Att":9,
    "TD":1,
    "20+":0,
    "40+":0,
    "Lng":10,
    "Rush 1st":4,
    "Rush 1st%":2.25,
    "Rush FUM":0
  },
  {
    "Player":"Robert Woods",
    "Rush Yds":46,
    "Att":8,
    "TD":1,
    "20+":0,
    "40+":0,
    "Lng":16,
    "Rush 1st":1,
    "Rush 1st%":8.0,
    "Rush FUM":0
  },
  {
    "Player":"Mecole Hardman",
    "Rush Yds":46,
    "Att":8,
    "TD":0,
    "20+":1,
    "40+":0,
    "Lng":24,
    "Rush 1st":2,
    "Rush 1st%":4.0,
    "Rush FUM":1
  },
  {
    "Player":"Michael Pittman",
    "Rush Yds":44,
    "Att":5,
    "TD":0,
    "20+":1,
    "40+":0,
    "Lng":25,
    "Rush 1st":1,
    "Rush 1st%":5.0,
    "Rush FUM":0
  },
  {
    "Player":"Ty Montgomery",
    "Rush Yds":44,
    "Att":15,
    "TD":0,
    "20+":0,
    "40+":0,
    "Lng":9,
    "Rush 1st":2,
    "Rush 1st%":7.5,
    "Rush FUM":0
  },
  {
    "Player":"Davis Mills",
    "Rush Yds":44,
    "Att":18,
    "TD":0,
    "20+":0,
    "40+":0,
    "Lng":11,
    "Rush 1st":5,
    "Rush 1st%":3.6,
    "Rush FUM":0
  },
  {
    "Player":"Matthew Stafford",
    "Rush Yds":43,
    "Att":32,
    "TD":0,
    "20+":0,
    "40+":0,
    "Lng":12,
    "Rush 1st":8,
    "Rush 1st%":4.0,
    "Rush FUM":1
  },
  {
    "Player":"Scott Miller",
    "Rush Yds":43,
    "Att":2,
    "TD":1,
    "20+":1,
    "40+":0,
    "Lng":33,
    "Rush 1st":2,
    "Rush 1st%":1.0,
    "Rush FUM":0
  },
  {
    "Player":"Geno Smith",
    "Rush Yds":42,
    "Att":9,
    "TD":1,
    "20+":0,
    "40+":0,
    "Lng":12,
    "Rush 1st":3,
    "Rush 1st%":3.0,
    "Rush FUM":0
  },
  {
    "Player":"Alex Armah",
    "Rush Yds":42,
    "Att":10,
    "TD":0,
    "20+":0,
    "40+":0,
    "Lng":18,
    "Rush 1st":8,
    "Rush 1st%":1.25,
    "Rush FUM":0
  },
  {
    "Player":"Laviska Shenault Jr.",
    "Rush Yds":41,
    "Att":11,
    "TD":0,
    "20+":0,
    "40+":0,
    "Lng":11,
    "Rush 1st":2,
    "Rush 1st%":5.5,
    "Rush FUM":0
  },
  {
    "Player":"Deonte Harris",
    "Rush Yds":41,
    "Att":5,
    "TD":0,
    "20+":1,
    "40+":0,
    "Lng":22,
    "Rush 1st":1,
    "Rush 1st%":5.0,
    "Rush FUM":0
  },
  {
    "Player":"Jonnu Smith",
    "Rush Yds":40,
    "Att":9,
    "TD":0,
    "20+":0,
    "40+":0,
    "Lng":9,
    "Rush 1st":2,
    "Rush 1st%":4.5,
    "Rush FUM":0
  },
  {
    "Player":"Jalen Richard",
    "Rush Yds":40,
    "Att":9,
    "TD":0,
    "20+":1,
    "40+":0,
    "Lng":23,
    "Rush 1st":3,
    "Rush 1st%":3.0,
    "Rush FUM":0
  },
  {
    "Player":"Jarvis Landry",
    "Rush Yds":40,
    "Att":6,
    "TD":2,
    "20+":0,
    "40+":0,
    "Lng":16,
    "Rush 1st":4,
    "Rush 1st%":1.5,
    "Rush FUM":1
  },
  {
    "Player":"Braxton Berrios",
    "Rush Yds":40,
    "Att":7,
    "TD":2,
    "20+":0,
    "40+":0,
    "Lng":11,
    "Rush 1st":3,
    "Rush 1st%":2.333,
    "Rush FUM":0
  },
  {
    "Player":"Anthony Schwartz",
    "Rush Yds":39,
    "Att":6,
    "TD":0,
    "20+":0,
    "40+":0,
    "Lng":17,
    "Rush 1st":4,
    "Rush 1st%":1.5,
    "Rush FUM":0
  },
  {
    "Player":"James White",
    "Rush Yds":38,
    "Att":10,
    "TD":1,
    "20+":0,
    "40+":0,
    "Lng":10,
    "Rush 1st":4,
    "Rush 1st%":2.5,
    "Rush FUM":0
  },
  {
    "Player":"J.J. Taylor",
    "Rush Yds":37,
    "Att":19,
    "TD":2,
    "20+":0,
    "40+":0,
    "Lng":15,
    "Rush 1st":3,
    "Rush 1st%":6.333,
    "Rush FUM":0
  },
  {
    "Player":"Colt McCoy",
    "Rush Yds":37,
    "Att":22,
    "TD":0,
    "20+":0,
    "40+":0,
    "Lng":11,
    "Rush 1st":6,
    "Rush 1st%":3.667,
    "Rush FUM":1
  },
  {
    "Player":"Kalen Ballage",
    "Rush Yds":36,
    "Att":11,
    "TD":0,
    "20+":0,
    "40+":0,
    "Lng":13,
    "Rush 1st":2,
    "Rush 1st%":5.5,
    "Rush FUM":0
  },
  {
    "Player":"Robby Anderson",
    "Rush Yds":36,
    "Att":3,
    "TD":0,
    "20+":1,
    "40+":0,
    "Lng":30,
    "Rush 1st":1,
    "Rush 1st%":3.0,
    "Rush FUM":0
  },
  {
    "Player":"Mike Boone",
    "Rush Yds":35,
    "Att":4,
    "TD":0,
    "20+":0,
    "40+":0,
    "Lng":16,
    "Rush 1st":2,
    "Rush 1st%":2.0,
    "Rush FUM":0
  },
  {
    "Player":"C.J. Ham",
    "Rush Yds":34,
    "Att":5,
    "TD":0,
    "20+":1,
    "40+":0,
    "Lng":30,
    "Rush 1st":3,
    "Rush 1st%":1.667,
    "Rush FUM":0
  },
  {
    "Player":"Jalen Guyton",
    "Rush Yds":34,
    "Att":7,
    "TD":0,
    "20+":1,
    "40+":0,
    "Lng":21,
    "Rush 1st":2,
    "Rush 1st%":3.5,
    "Rush FUM":1
  },
  {
    "Player":"Jonathan Ward",
    "Rush Yds":33,
    "Att":9,
    "TD":0,
    "20+":0,
    "40+":0,
    "Lng":7,
    "Rush 1st":3,
    "Rush 1st%":3.0,
    "Rush FUM":0
  },
  {
    "Player":"Jakeem Grant",
    "Rush Yds":33,
    "Att":5,
    "TD":0,
    "20+":0,
    "40+":0,
    "Lng":13,
    "Rush 1st":2,
    "Rush 1st%":2.5,
    "Rush FUM":0
  },
  {
    "Player":"Mike Glennon",
    "Rush Yds":33,
    "Att":7,
    "TD":1,
    "20+":0,
    "40+":0,
    "Lng":13,
    "Rush 1st":2,
    "Rush 1st%":3.5,
    "Rush FUM":1
  },
  {
    "Player":"Freddie Swain",
    "Rush Yds":32,
    "Att":5,
    "TD":0,
    "20+":0,
    "40+":0,
    "Lng":11,
    "Rush 1st":2,
    "Rush 1st%":2.5,
    "Rush FUM":0
  },
  {
    "Player":"Jalen Reagor",
    "Rush Yds":32,
    "Att":10,
    "TD":0,
    "20+":0,
    "40+":0,
    "Lng":12,
    "Rush 1st":3,
    "Rush 1st%":3.333,
    "Rush FUM":0
  },
  {
    "Player":"Darnell Mooney",
    "Rush Yds":32,
    "Att":6,
    "TD":1,
    "20+":0,
    "40+":0,
    "Lng":15,
    "Rush 1st":2,
    "Rush 1st%":3.0,
    "Rush FUM":0
  },
  {
    "Player":"Allen Lazard",
    "Rush Yds":32,
    "Att":3,
    "TD":0,
    "20+":0,
    "40+":0,
    "Lng":14,
    "Rush 1st":2,
    "Rush 1st%":1.5,
    "Rush FUM":0
  },
  {
    "Player":"Ashton Dulin",
    "Rush Yds":32,
    "Att":3,
    "TD":0,
    "20+":1,
    "40+":0,
    "Lng":37,
    "Rush 1st":1,
    "Rush 1st%":3.0,
    "Rush FUM":0
  },
  {
    "Player":"Keith Smith",
    "Rush Yds":31,
    "Att":9,
    "TD":0,
    "20+":0,
    "40+":0,
    "Lng":8,
    "Rush 1st":3,
    "Rush 1st%":3.0,
    "Rush FUM":0
  },
  {
    "Player":"Emmanuel Sanders",
    "Rush Yds":31,
    "Att":2,
    "TD":0,
    "20+":1,
    "40+":0,
    "Lng":24,
    "Rush 1st":2,
    "Rush 1st%":1.0,
    "Rush FUM":0
  },
  {
    "Player":"La'Mical Perine",
    "Rush Yds":31,
    "Att":8,
    "TD":0,
    "20+":0,
    "40+":0,
    "Lng":14,
    "Rush 1st":1,
    "Rush 1st%":8.0,
    "Rush FUM":0
  },
  {
    "Player":"Deon Jackson",
    "Rush Yds":31,
    "Att":12,
    "TD":1,
    "20+":0,
    "40+":0,
    "Lng":10,
    "Rush 1st":2,
    "Rush 1st%":6.0,
    "Rush FUM":0
  },
  {
    "Player":"JaQuan Hardy",
    "Rush Yds":29,
    "Att":4,
    "TD":1,
    "20+":1,
    "40+":0,
    "Lng":22,
    "Rush 1st":1,
    "Rush 1st%":4.0,
    "Rush FUM":0
  },
  {
    "Player":"Kalif Raymond",
    "Rush Yds":28,
    "Att":4,
    "TD":0,
    "20+":0,
    "40+":0,
    "Lng":13,
    "Rush 1st":2,
    "Rush 1st%":2.0,
    "Rush FUM":0
  },
  {
    "Player":"C.J. Moore",
    "Rush Yds":28,
    "Att":1,
    "TD":0,
    "20+":1,
    "40+":0,
    "Lng":28,
    "Rush 1st":1,
    "Rush 1st%":1.0,
    "Rush FUM":0
  },
  {
    "Player":"Josh Johnson",
    "Rush Yds":28,
    "Att":9,
    "TD":0,
    "20+":0,
    "40+":0,
    "Lng":18,
    "Rush 1st":1,
    "Rush 1st%":9.0,
    "Rush FUM":2
  },
  {
    "Player":"Odell Beckham Jr.",
    "Rush Yds":28,
    "Att":4,
    "TD":0,
    "20+":0,
    "40+":0,
    "Lng":20,
    "Rush 1st":2,
    "Rush 1st%":2.0,
    "Rush FUM":0
  },
  {
    "Player":"Jordan Love",
    "Rush Yds":27,
    "Att":12,
    "TD":0,
    "20+":0,
    "40+":0,
    "Lng":10,
    "Rush 1st":1,
    "Rush 1st%":12.0,
    "Rush FUM":1
  },
  {
    "Player":"Michael Burton",
    "Rush Yds":26,
    "Att":8,
    "TD":1,
    "20+":0,
    "40+":0,
    "Lng":7,
    "Rush 1st":8,
    "Rush 1st%":1.0,
    "Rush FUM":0
  },
  {
    "Player":"Wendell Smallwood",
    "Rush Yds":25,
    "Att":5,
    "TD":0,
    "20+":0,
    "40+":0,
    "Lng":13,
    "Rush 1st":2,
    "Rush 1st%":2.5,
    "Rush FUM":0
  },
  {
    "Player":"Mitchell Trubisky",
    "Rush Yds":24,
    "Att":13,
    "TD":1,
    "20+":1,
    "40+":0,
    "Lng":22,
    "Rush 1st":3,
    "Rush 1st%":4.333,
    "Rush FUM":0
  },
  {
    "Player":"Kylin Hill",
    "Rush Yds":24,
    "Att":10,
    "TD":0,
    "20+":0,
    "40+":0,
    "Lng":8,
    "Rush 1st":1,
    "Rush 1st%":10.0,
    "Rush FUM":0
  },
  {
    "Player":"Demetric Felton",
    "Rush Yds":24,
    "Att":7,
    "TD":0,
    "20+":0,
    "40+":0,
    "Lng":12,
    "Rush 1st":0,
    "Rush 1st%":0.0,
    "Rush FUM":0
  },
  {
    "Player":"Greg Dortch",
    "Rush Yds":24,
    "Att":1,
    "TD":0,
    "20+":1,
    "40+":0,
    "Lng":24,
    "Rush 1st":1,
    "Rush 1st%":1.0,
    "Rush FUM":0
  },
  {
    "Player":"Jason Cabinda",
    "Rush Yds":23,
    "Att":3,
    "TD":0,
    "20+":1,
    "40+":0,
    "Lng":21,
    "Rush 1st":2,
    "Rush 1st%":1.5,
    "Rush FUM":0
  },
  {
    "Player":"Case Keenum",
    "Rush Yds":22,
    "Att":12,
    "TD":0,
    "20+":0,
    "40+":0,
    "Lng":10,
    "Rush 1st":6,
    "Rush 1st%":2.0,
    "Rush FUM":0
  },
  {
    "Player":"Kyle Juszczyk",
    "Rush Yds":22,
    "Att":8,
    "TD":1,
    "20+":0,
    "40+":0,
    "Lng":6,
    "Rush 1st":3,
    "Rush 1st%":2.667,
    "Rush FUM":0
  },
  {
    "Player":"Tyler Boyd",
    "Rush Yds":22,
    "Att":2,
    "TD":0,
    "20+":0,
    "40+":0,
    "Lng":14,
    "Rush 1st":1,
    "Rush 1st%":2.0,
    "Rush FUM":0
  },
  {
    "Player":"Zach Pascal",
    "Rush Yds":21,
    "Att":2,
    "TD":0,
    "20+":0,
    "40+":0,
    "Lng":12,
    "Rush 1st":0,
    "Rush 1st%":0.0,
    "Rush FUM":0
  },
  {
    "Player":"Gardner Minshew",
    "Rush Yds":21,
    "Att":9,
    "TD":0,
    "20+":0,
    "40+":0,
    "Lng":9,
    "Rush 1st":2,
    "Rush 1st%":4.5,
    "Rush FUM":0
  },
  {
    "Player":"Chris Godwin",
    "Rush Yds":21,
    "Att":4,
    "TD":1,
    "20+":0,
    "40+":0,
    "Lng":9,
    "Rush 1st":4,
    "Rush 1st%":1.0,
    "Rush FUM":0
  },
  {
    "Player":"Brandin Cooks",
    "Rush Yds":21,
    "Att":2,
    "TD":0,
    "20+":0,
    "40+":0,
    "Lng":16,
    "Rush 1st":1,
    "Rush 1st%":2.0,
    "Rush FUM":0
  },
  {
    "Player":"Ja'Marr Chase",
    "Rush Yds":21,
    "Att":7,
    "TD":0,
    "20+":0,
    "40+":0,
    "Lng":10,
    "Rush 1st":2,
    "Rush 1st%":3.5,
    "Rush FUM":0
  },
  {
    "Player":"Tavon Austin",
    "Rush Yds":21,
    "Att":3,
    "TD":0,
    "20+":0,
    "40+":0,
    "Lng":8,
    "Rush 1st":1,
    "Rush 1st%":3.0,
    "Rush FUM":0
  },
  {
    "Player":"Trevor Siemian",
    "Rush Yds":20,
    "Att":9,
    "TD":1,
    "20+":0,
    "40+":0,
    "Lng":17,
    "Rush 1st":2,
    "Rush 1st%":4.5,
    "Rush FUM":0
  },
  {
    "Player":"Raheem Mostert",
    "Rush Yds":20,
    "Att":2,
    "TD":0,
    "20+":0,
    "40+":0,
    "Lng":11,
    "Rush 1st":1,
    "Rush 1st%":2.0,
    "Rush FUM":0
  },
  {
    "Player":"George Kittle",
    "Rush Yds":20,
    "Att":3,
    "TD":0,
    "20+":0,
    "40+":0,
    "Lng":9,
    "Rush 1st":0,
    "Rush 1st%":0.0,
    "Rush FUM":0
  },
  {
    "Player":"Van Jefferson",
    "Rush Yds":20,
    "Att":2,
    "TD":0,
    "20+":0,
    "40+":0,
    "Lng":10,
    "Rush 1st":1,
    "Rush 1st%":2.0,
    "Rush FUM":0
  },
  {
    "Player":"Gerald Everett",
    "Rush Yds":20,
    "Att":3,
    "TD":0,
    "20+":0,
    "40+":0,
    "Lng":13,
    "Rush 1st":2,
    "Rush 1st%":1.5,
    "Rush FUM":0
  },
  {
    "Player":"Mekhi Sargent",
    "Rush Yds":19,
    "Att":9,
    "TD":0,
    "20+":0,
    "40+":0,
    "Lng":11,
    "Rush 1st":3,
    "Rush 1st%":3.0,
    "Rush FUM":0
  },
  {
    "Player":"Andre Roberts",
    "Rush Yds":19,
    "Att":3,
    "TD":0,
    "20+":0,
    "40+":0,
    "Lng":9,
    "Rush 1st":0,
    "Rush 1st%":0.0,
    "Rush FUM":0
  },
  {
    "Player":"Cooper Kupp",
    "Rush Yds":18,
    "Att":4,
    "TD":0,
    "20+":0,
    "40+":0,
    "Lng":18,
    "Rush 1st":1,
    "Rush 1st%":4.0,
    "Rush FUM":0
  },
  {
    "Player":"Albert Wilson",
    "Rush Yds":17,
    "Att":4,
    "TD":0,
    "20+":0,
    "40+":0,
    "Lng":14,
    "Rush 1st":1,
    "Rush 1st%":4.0,
    "Rush FUM":0
  },
  {
    "Player":"Brandon Aiyuk",
    "Rush Yds":17,
    "Att":5,
    "TD":0,
    "20+":0,
    "40+":0,
    "Lng":8,
    "Rush 1st":0,
    "Rush 1st%":0.0,
    "Rush FUM":0
  },
  {
    "Player":"Dwayne Washington",
    "Rush Yds":16,
    "Att":4,
    "TD":0,
    "20+":0,
    "40+":0,
    "Lng":5,
    "Rush 1st":0,
    "Rush 1st%":0.0,
    "Rush FUM":0
  },
  {
    "Player":"Henry Ruggs III",
    "Rush Yds":16,
    "Att":3,
    "TD":0,
    "20+":0,
    "40+":0,
    "Lng":7,
    "Rush 1st":0,
    "Rush 1st%":0.0,
    "Rush FUM":0
  },
  {
    "Player":"John Ross",
    "Rush Yds":16,
    "Att":1,
    "TD":0,
    "20+":0,
    "40+":0,
    "Lng":16,
    "Rush 1st":1,
    "Rush 1st%":1.0,
    "Rush FUM":0
  },
  {
    "Player":"Ray-Ray McCloud",
    "Rush Yds":15,
    "Att":2,
    "TD":0,
    "20+":0,
    "40+":0,
    "Lng":10,
    "Rush 1st":0,
    "Rush 1st%":0.0,
    "Rush FUM":0
  },
  {
    "Player":"Cameron Batson",
    "Rush Yds":15,
    "Att":2,
    "TD":0,
    "20+":0,
    "40+":0,
    "Lng":11,
    "Rush 1st":1,
    "Rush 1st%":2.0,
    "Rush FUM":0
  },
  {
    "Player":"Equanimeous St. Brown",
    "Rush Yds":14,
    "Att":3,
    "TD":0,
    "20+":0,
    "40+":0,
    "Lng":13,
    "Rush 1st":2,
    "Rush 1st%":1.5,
    "Rush FUM":0
  },
  {
    "Player":"Sean Mannion",
    "Rush Yds":14,
    "Att":2,
    "TD":0,
    "20+":0,
    "40+":0,
    "Lng":11,
    "Rush 1st":2,
    "Rush 1st%":1.0,
    "Rush FUM":0
  },
  {
    "Player":"Justin Jefferson",
    "Rush Yds":14,
    "Att":6,
    "TD":0,
    "20+":0,
    "40+":0,
    "Lng":11,
    "Rush 1st":1,
    "Rush 1st%":6.0,
    "Rush FUM":0
  },
  {
    "Player":"Cyril Grayson",
    "Rush Yds":14,
    "Att":1,
    "TD":0,
    "20+":0,
    "40+":0,
    "Lng":14,
    "Rush 1st":1,
    "Rush 1st%":1.0,
    "Rush FUM":0
  },
  {
    "Player":"Sean Chandler",
    "Rush Yds":14,
    "Att":1,
    "TD":0,
    "20+":0,
    "40+":0,
    "Lng":14,
    "Rush 1st":1,
    "Rush 1st%":1.0,
    "Rush FUM":0
  },
  {
    "Player":"James Washington",
    "Rush Yds":13,
    "Att":2,
    "TD":0,
    "20+":0,
    "40+":0,
    "Lng":12,
    "Rush 1st":1,
    "Rush 1st%":2.0,
    "Rush FUM":0
  },
  {
    "Player":"P.J. Walker",
    "Rush Yds":13,
    "Att":7,
    "TD":0,
    "20+":0,
    "40+":0,
    "Lng":13,
    "Rush 1st":2,
    "Rush 1st%":3.5,
    "Rush FUM":2
  },
  {
    "Player":"Scottie Phillips",
    "Rush Yds":13,
    "Att":6,
    "TD":0,
    "20+":0,
    "40+":0,
    "Lng":4,
    "Rush 1st":1,
    "Rush 1st%":6.0,
    "Rush FUM":0
  },
  {
    "Player":"John Kelly",
    "Rush Yds":13,
    "Att":2,
    "TD":0,
    "20+":0,
    "40+":0,
    "Lng":11,
    "Rush 1st":1,
    "Rush 1st%":2.0,
    "Rush FUM":0
  },
  {
    "Player":"Tim Boyle",
    "Rush Yds":13,
    "Att":2,
    "TD":0,
    "20+":0,
    "40+":0,
    "Lng":14,
    "Rush 1st":1,
    "Rush 1st%":2.0,
    "Rush FUM":0
  },
  {
    "Player":"Jacques Patrick",
    "Rush Yds":12,
    "Att":2,
    "TD":0,
    "20+":0,
    "40+":0,
    "Lng":8,
    "Rush 1st":1,
    "Rush 1st%":2.0,
    "Rush FUM":0
  },
  {
    "Player":"Terry McLaurin",
    "Rush Yds":12,
    "Att":1,
    "TD":0,
    "20+":0,
    "40+":0,
    "Lng":12,
    "Rush 1st":1,
    "Rush 1st%":1.0,
    "Rush FUM":0
  },
  {
    "Player":"Ced Wilson",
    "Rush Yds":11,
    "Att":2,
    "TD":0,
    "20+":0,
    "40+":0,
    "Lng":6,
    "Rush 1st":1,
    "Rush 1st%":2.0,
    "Rush FUM":0
  },
  {
    "Player":"Tommy Tremble",
    "Rush Yds":11,
    "Att":3,
    "TD":1,
    "20+":0,
    "40+":0,
    "Lng":7,
    "Rush 1st":1,
    "Rush 1st%":3.0,
    "Rush FUM":0
  },
  {
    "Player":"Curtis Samuel",
    "Rush Yds":11,
    "Att":4,
    "TD":0,
    "20+":0,
    "40+":0,
    "Lng":8,
    "Rush 1st":0,
    "Rush 1st%":0.0,
    "Rush FUM":0
  },
  {
    "Player":"Amari Rodgers",
    "Rush Yds":11,
    "Att":1,
    "TD":0,
    "20+":0,
    "40+":0,
    "Lng":11,
    "Rush 1st":1,
    "Rush 1st%":1.0,
    "Rush FUM":0
  },
  {
    "Player":"Christian Kirk",
    "Rush Yds":11,
    "Att":1,
    "TD":0,
    "20+":0,
    "40+":0,
    "Lng":11,
    "Rush 1st":1,
    "Rush 1st%":1.0,
    "Rush FUM":0
  },
  {
    "Player":"Buddy Howell",
    "Rush Yds":11,
    "Att":5,
    "TD":0,
    "20+":0,
    "40+":0,
    "Lng":4,
    "Rush 1st":0,
    "Rush 1st%":0.0,
    "Rush FUM":0
  },
  {
    "Player":"Jaelon Darden",
    "Rush Yds":11,
    "Att":1,
    "TD":0,
    "20+":0,
    "40+":0,
    "Lng":11,
    "Rush 1st":1,
    "Rush 1st%":1.0,
    "Rush FUM":0
  },
  {
    "Player":"Kyle Allen",
    "Rush Yds":11,
    "Att":2,
    "TD":0,
    "20+":0,
    "40+":0,
    "Lng":11,
    "Rush 1st":1,
    "Rush 1st%":2.0,
    "Rush FUM":0
  },
  {
    "Player":"Nelson Agholor",
    "Rush Yds":11,
    "Att":3,
    "TD":0,
    "20+":0,
    "40+":0,
    "Lng":6,
    "Rush 1st":0,
    "Rush 1st%":0.0,
    "Rush FUM":0
  },
  {
    "Player":"K.J. Osborn",
    "Rush Yds":10,
    "Att":1,
    "TD":0,
    "20+":0,
    "40+":0,
    "Lng":10,
    "Rush 1st":1,
    "Rush 1st%":1.0,
    "Rush FUM":0
  },
  {
    "Player":"Mike Evans",
    "Rush Yds":10,
    "Att":1,
    "TD":0,
    "20+":0,
    "40+":0,
    "Lng":10,
    "Rush 1st":1,
    "Rush 1st%":1.0,
    "Rush FUM":0
  },
  {
    "Player":"A.J. Brown",
    "Rush Yds":10,
    "Att":2,
    "TD":0,
    "20+":0,
    "40+":0,
    "Lng":7,
    "Rush 1st":1,
    "Rush 1st%":2.0,
    "Rush FUM":0
  },
  {
    "Player":"Blake Bell",
    "Rush Yds":10,
    "Att":4,
    "TD":0,
    "20+":0,
    "40+":0,
    "Lng":3,
    "Rush 1st":4,
    "Rush 1st%":1.0,
    "Rush FUM":0
  },
  {
    "Player":"JuJu Smith-Schuster",
    "Rush Yds":9,
    "Att":3,
    "TD":1,
    "20+":0,
    "40+":0,
    "Lng":3,
    "Rush 1st":1,
    "Rush 1st%":3.0,
    "Rush FUM":0
  },
  {
    "Player":"Jaylen Samuels",
    "Rush Yds":9,
    "Att":5,
    "TD":0,
    "20+":0,
    "40+":0,
    "Lng":3,
    "Rush 1st":0,
    "Rush 1st%":0.0,
    "Rush FUM":0
  },
  {
    "Player":"Chester Rogers",
    "Rush Yds":9,
    "Att":1,
    "TD":0,
    "20+":0,
    "40+":0,
    "Lng":9,
    "Rush 1st":0,
    "Rush 1st%":0.0,
    "Rush FUM":0
  },
  {
    "Player":"Trey Ragas",
    "Rush Yds":9,
    "Att":1,
    "TD":0,
    "20+":0,
    "40+":0,
    "Lng":9,
    "Rush 1st":1,
    "Rush 1st%":1.0,
    "Rush FUM":0
  },
  {
    "Player":"Gunner Olszewski",
    "Rush Yds":9,
    "Att":1,
    "TD":0,
    "20+":0,
    "40+":0,
    "Lng":9,
    "Rush 1st":0,
    "Rush 1st%":0.0,
    "Rush FUM":0
  },
  {
    "Player":"Jakobi Meyers",
    "Rush Yds":9,
    "Att":1,
    "TD":0,
    "20+":0,
    "40+":0,
    "Lng":9,
    "Rush 1st":0,
    "Rush 1st%":0.0,
    "Rush FUM":0
  },
  {
    "Player":"Tyler Lockett",
    "Rush Yds":9,
    "Att":2,
    "TD":0,
    "20+":0,
    "40+":0,
    "Lng":7,
    "Rush 1st":0,
    "Rush 1st%":0.0,
    "Rush FUM":0
  },
  {
    "Player":"Sam Ehlinger",
    "Rush Yds":9,
    "Att":3,
    "TD":0,
    "20+":0,
    "40+":0,
    "Lng":9,
    "Rush 1st":1,
    "Rush 1st%":3.0,
    "Rush FUM":0
  },
  {
    "Player":"Gabe Nabers",
    "Rush Yds":8,
    "Att":3,
    "TD":0,
    "20+":0,
    "40+":0,
    "Lng":4,
    "Rush 1st":1,
    "Rush 1st%":3.0,
    "Rush FUM":0
  },
  {
    "Player":"Nick Foles",
    "Rush Yds":8,
    "Att":4,
    "TD":0,
    "20+":0,
    "40+":0,
    "Lng":8,
    "Rush 1st":1,
    "Rush 1st%":4.0,
    "Rush FUM":0
  },
  {
    "Player":"Preston Williams",
    "Rush Yds":7,
    "Att":1,
    "TD":0,
    "20+":0,
    "40+":0,
    "Lng":7,
    "Rush 1st":0,
    "Rush 1st%":0.0,
    "Rush FUM":0
  },
  {
    "Player":"Tremon Smith",
    "Rush Yds":7,
    "Att":1,
    "TD":0,
    "20+":0,
    "40+":0,
    "Lng":7,
    "Rush 1st":0,
    "Rush 1st%":0.0,
    "Rush FUM":0
  },
  {
    "Player":"Cam Sims",
    "Rush Yds":7,
    "Att":1,
    "TD":0,
    "20+":0,
    "40+":0,
    "Lng":7,
    "Rush 1st":0,
    "Rush 1st%":0.0,
    "Rush FUM":0
  },
  {
    "Player":"Darrynton Evans",
    "Rush Yds":7,
    "Att":2,
    "TD":0,
    "20+":0,
    "40+":0,
    "Lng":5,
    "Rush 1st":0,
    "Rush 1st%":0.0,
    "Rush FUM":0
  },
  {
    "Player":"Damarea Crockett",
    "Rush Yds":7,
    "Att":3,
    "TD":0,
    "20+":0,
    "40+":0,
    "Lng":6,
    "Rush 1st":0,
    "Rush 1st%":0.0,
    "Rush FUM":0
  },
  {
    "Player":"Kadarius Toney",
    "Rush Yds":6,
    "Att":3,
    "TD":0,
    "20+":0,
    "40+":0,
    "Lng":7,
    "Rush 1st":0,
    "Rush 1st%":0.0,
    "Rush FUM":0
  },
  {
    "Player":"Chris Streveler",
    "Rush Yds":6,
    "Att":3,
    "TD":0,
    "20+":0,
    "40+":0,
    "Lng":4,
    "Rush 1st":0,
    "Rush 1st%":0.0,
    "Rush FUM":1
  },
  {
    "Player":"Josh Palmer",
    "Rush Yds":6,
    "Att":1,
    "TD":0,
    "20+":0,
    "40+":0,
    "Lng":6,
    "Rush 1st":0,
    "Rush 1st%":0.0,
    "Rush FUM":0
  },
  {
    "Player":"DK Metcalf",
    "Rush Yds":6,
    "Att":1,
    "TD":0,
    "20+":0,
    "40+":0,
    "Lng":6,
    "Rush 1st":0,
    "Rush 1st%":0.0,
    "Rush FUM":0
  },
  {
    "Player":"Dallin Leavitt",
    "Rush Yds":6,
    "Att":2,
    "TD":0,
    "20+":0,
    "40+":0,
    "Lng":4,
    "Rush 1st":2,
    "Rush 1st%":1.0,
    "Rush FUM":0
  },
  {
    "Player":"Feleipe Franks",
    "Rush Yds":6,
    "Att":3,
    "TD":0,
    "20+":0,
    "40+":0,
    "Lng":4,
    "Rush 1st":0,
    "Rush 1st%":0.0,
    "Rush FUM":0
  },
  {
    "Player":"Antonio Brown",
    "Rush Yds":6,
    "Att":1,
    "TD":0,
    "20+":0,
    "40+":0,
    "Lng":6,
    "Rush 1st":0,
    "Rush 1st%":0.0,
    "Rush FUM":0
  },
  {
    "Player":"Ian Book",
    "Rush Yds":6,
    "Att":3,
    "TD":0,
    "20+":0,
    "40+":0,
    "Lng":3,
    "Rush 1st":1,
    "Rush 1st%":3.0,
    "Rush FUM":0
  },
  {
    "Player":"C.J. Board",
    "Rush Yds":6,
    "Att":1,
    "TD":0,
    "20+":0,
    "40+":0,
    "Lng":6,
    "Rush 1st":0,
    "Rush 1st%":0.0,
    "Rush FUM":0
  },
  {
    "Player":"David Blough",
    "Rush Yds":6,
    "Att":1,
    "TD":0,
    "20+":0,
    "40+":0,
    "Lng":6,
    "Rush 1st":0,
    "Rush 1st%":0.0,
    "Rush FUM":0
  },
  {
    "Player":"Khari Blasingame",
    "Rush Yds":6,
    "Att":3,
    "TD":0,
    "20+":0,
    "40+":0,
    "Lng":3,
    "Rush 1st":1,
    "Rush 1st%":3.0,
    "Rush FUM":1
  },
  {
    "Player":"Johnny Stanton",
    "Rush Yds":5,
    "Att":2,
    "TD":0,
    "20+":0,
    "40+":0,
    "Lng":3,
    "Rush 1st":2,
    "Rush 1st%":1.0,
    "Rush FUM":0
  },
  {
    "Player":"Ben Roethlisberger",
    "Rush Yds":5,
    "Att":20,
    "TD":1,
    "20+":0,
    "40+":0,
    "Lng":8,
    "Rush 1st":3,
    "Rush 1st%":6.667,
    "Rush FUM":0
  },
  {
    "Player":"Adam Prentice",
    "Rush Yds":5,
    "Att":3,
    "TD":0,
    "20+":0,
    "40+":0,
    "Lng":2,
    "Rush 1st":2,
    "Rush 1st%":1.5,
    "Rush FUM":0
  },
  {
    "Player":"Jake Funk",
    "Rush Yds":5,
    "Att":2,
    "TD":0,
    "20+":0,
    "40+":0,
    "Lng":6,
    "Rush 1st":0,
    "Rush 1st%":0.0,
    "Rush FUM":0
  },
  {
    "Player":"Marquise Brown",
    "Rush Yds":5,
    "Att":1,
    "TD":0,
    "20+":0,
    "40+":0,
    "Lng":5,
    "Rush 1st":1,
    "Rush 1st%":1.0,
    "Rush FUM":0
  },
  {
    "Player":"Andrew Wingard",
    "Rush Yds":4,
    "Att":1,
    "TD":0,
    "20+":0,
    "40+":0,
    "Lng":4,
    "Rush 1st":1,
    "Rush 1st%":1.0,
    "Rush FUM":0
  },
  {
    "Player":"Ito Smith",
    "Rush Yds":4,
    "Att":1,
    "TD":1,
    "20+":0,
    "40+":0,
    "Lng":4,
    "Rush 1st":1,
    "Rush 1st%":1.0,
    "Rush FUM":0
  },
  {
    "Player":"Patrick Ricard",
    "Rush Yds":4,
    "Att":2,
    "TD":0,
    "20+":0,
    "40+":0,
    "Lng":2,
    "Rush 1st":2,
    "Rush 1st%":1.0,
    "Rush FUM":0
  },
  {
    "Player":"Ryan Nall",
    "Rush Yds":4,
    "Att":1,
    "TD":0,
    "20+":0,
    "40+":0,
    "Lng":4,
    "Rush 1st":0,
    "Rush 1st%":0.0,
    "Rush FUM":0
  },
  {
    "Player":"Braden Mann",
    "Rush Yds":4,
    "Att":1,
    "TD":0,
    "20+":0,
    "40+":0,
    "Lng":4,
    "Rush 1st":0,
    "Rush 1st%":0.0,
    "Rush FUM":0
  },
  {
    "Player":"Patrick Laird",
    "Rush Yds":4,
    "Att":1,
    "TD":0,
    "20+":0,
    "40+":0,
    "Lng":4,
    "Rush 1st":0,
    "Rush 1st%":0.0,
    "Rush FUM":0
  },
  {
    "Player":"Dawson Knox",
    "Rush Yds":4,
    "Att":0,
    "TD":0,
    "20+":0,
    "40+":0,
    "Lng":4,
    "Rush 1st":1,
    "Rush 1st%":0.0,
    "Rush FUM":0
  },
  {
    "Player":"DeSean Jackson",
    "Rush Yds":4,
    "Att":1,
    "TD":0,
    "20+":0,
    "40+":0,
    "Lng":4,
    "Rush 1st":0,
    "Rush 1st%":0.0,
    "Rush FUM":0
  },
  {
    "Player":"Zach Ertz",
    "Rush Yds":4,
    "Att":1,
    "TD":0,
    "20+":0,
    "40+":0,
    "Lng":4,
    "Rush 1st":0,
    "Rush 1st%":0.0,
    "Rush FUM":0
  },
  {
    "Player":"Trenton Cannon",
    "Rush Yds":4,
    "Att":3,
    "TD":0,
    "20+":0,
    "40+":0,
    "Lng":2,
    "Rush 1st":0,
    "Rush 1st%":0.0,
    "Rush FUM":0
  },
  {
    "Player":"Gary Brightwell",
    "Rush Yds":4,
    "Att":1,
    "TD":0,
    "20+":0,
    "40+":0,
    "Lng":4,
    "Rush 1st":0,
    "Rush 1st%":0.0,
    "Rush FUM":0
  },
  {
    "Player":"Reggie Bonnafon",
    "Rush Yds":4,
    "Att":1,
    "TD":0,
    "20+":0,
    "40+":0,
    "Lng":4,
    "Rush 1st":0,
    "Rush 1st%":0.0,
    "Rush FUM":0
  },
  {
    "Player":"Quez Watkins",
    "Rush Yds":3,
    "Att":1,
    "TD":0,
    "20+":0,
    "40+":0,
    "Lng":3,
    "Rush 1st":0,
    "Rush 1st%":0.0,
    "Rush FUM":0
  },
  {
    "Player":"Jaylen Waddle",
    "Rush Yds":3,
    "Att":2,
    "TD":1,
    "20+":0,
    "40+":0,
    "Lng":2,
    "Rush 1st":1,
    "Rush 1st%":2.0,
    "Rush FUM":0
  },
  {
    "Player":"Durham Smythe",
    "Rush Yds":3,
    "Att":2,
    "TD":0,
    "20+":0,
    "40+":0,
    "Lng":2,
    "Rush 1st":2,
    "Rush 1st%":1.0,
    "Rush FUM":0
  },
  {
    "Player":"Hunter Renfrow",
    "Rush Yds":3,
    "Att":3,
    "TD":0,
    "20+":0,
    "40+":0,
    "Lng":5,
    "Rush 1st":0,
    "Rush 1st%":0.0,
    "Rush FUM":0
  },
  {
    "Player":"Stanley Morgan",
    "Rush Yds":3,
    "Att":1,
    "TD":0,
    "20+":0,
    "40+":0,
    "Lng":3,
    "Rush 1st":0,
    "Rush 1st%":0.0,
    "Rush FUM":0
  },
  {
    "Player":"Anthony McFarland",
    "Rush Yds":3,
    "Att":3,
    "TD":0,
    "20+":0,
    "40+":0,
    "Lng":3,
    "Rush 1st":0,
    "Rush 1st%":0.0,
    "Rush FUM":0
  },
  {
    "Player":"Travis Kelce",
    "Rush Yds":3,
    "Att":2,
    "TD":1,
    "20+":0,
    "40+":0,
    "Lng":4,
    "Rush 1st":1,
    "Rush 1st%":2.0,
    "Rush FUM":0
  },
  {
    "Player":"Zay Jones",
    "Rush Yds":3,
    "Att":2,
    "TD":0,
    "20+":0,
    "40+":0,
    "Lng":4,
    "Rush 1st":0,
    "Rush 1st%":0.0,
    "Rush FUM":0
  },
  {
    "Player":"Jerry Jeudy",
    "Rush Yds":3,
    "Att":2,
    "TD":0,
    "20+":0,
    "40+":0,
    "Lng":3,
    "Rush 1st":0,
    "Rush 1st%":0.0,
    "Rush FUM":0
  },
  {
    "Player":"Reggie Gilliam",
    "Rush Yds":3,
    "Att":3,
    "TD":0,
    "20+":0,
    "40+":0,
    "Lng":2,
    "Rush 1st":0,
    "Rush 1st%":0.0,
    "Rush FUM":0
  },
  {
    "Player":"Maurice Ffrench",
    "Rush Yds":3,
    "Att":1,
    "TD":0,
    "20+":0,
    "40+":0,
    "Lng":3,
    "Rush 1st":0,
    "Rush 1st%":0.0,
    "Rush FUM":0
  },
  {
    "Player":"Joe Flacco",
    "Rush Yds":3,
    "Att":2,
    "TD":0,
    "20+":0,
    "40+":0,
    "Lng":2,
    "Rush 1st":1,
    "Rush 1st%":2.0,
    "Rush FUM":0
  },
  {
    "Player":"Nathan Cottrell",
    "Rush Yds":3,
    "Att":1,
    "TD":0,
    "20+":0,
    "40+":0,
    "Lng":3,
    "Rush 1st":0,
    "Rush 1st%":0.0,
    "Rush FUM":0
  },
  {
    "Player":"Pharoh Cooper",
    "Rush Yds":3,
    "Att":1,
    "TD":0,
    "20+":0,
    "40+":0,
    "Lng":3,
    "Rush 1st":0,
    "Rush 1st%":0.0,
    "Rush FUM":0
  },
  {
    "Player":"Chris Conley",
    "Rush Yds":3,
    "Att":1,
    "TD":0,
    "20+":0,
    "40+":0,
    "Lng":3,
    "Rush 1st":1,
    "Rush 1st%":1.0,
    "Rush FUM":0
  },
  {
    "Player":"Jordan Akins",
    "Rush Yds":3,
    "Att":1,
    "TD":0,
    "20+":0,
    "40+":0,
    "Lng":3,
    "Rush 1st":1,
    "Rush 1st%":1.0,
    "Rush FUM":0
  },
  {
    "Player":"Cam Akers",
    "Rush Yds":3,
    "Att":5,
    "TD":0,
    "20+":0,
    "40+":0,
    "Lng":2,
    "Rush 1st":0,
    "Rush 1st%":0.0,
    "Rush FUM":0
  },
  {
    "Player":"Olamide Zaccheaus",
    "Rush Yds":2,
    "Att":1,
    "TD":0,
    "20+":0,
    "40+":0,
    "Lng":2,
    "Rush 1st":1,
    "Rush 1st%":1.0,
    "Rush FUM":0
  },
  {
    "Player":"Adam Thielen",
    "Rush Yds":2,
    "Att":1,
    "TD":0,
    "20+":0,
    "40+":0,
    "Lng":2,
    "Rush 1st":0,
    "Rush 1st%":0.0,
    "Rush FUM":0
  },
  {
    "Player":"Nathan Peterman",
    "Rush Yds":2,
    "Att":2,
    "TD":0,
    "20+":0,
    "40+":0,
    "Lng":1,
    "Rush 1st":1,
    "Rush 1st%":2.0,
    "Rush FUM":0
  },
  {
    "Player":"Ryan Fitzpatrick",
    "Rush Yds":2,
    "Att":1,
    "TD":0,
    "20+":0,
    "40+":0,
    "Lng":2,
    "Rush 1st":0,
    "Rush 1st%":0.0,
    "Rush FUM":0
  },
  {
    "Player":"C.J. Beathard",
    "Rush Yds":2,
    "Att":1,
    "TD":0,
    "20+":0,
    "40+":0,
    "Lng":2,
    "Rush 1st":0,
    "Rush 1st%":0.0,
    "Rush FUM":0
  },
  {
    "Player":"Derek Watt",
    "Rush Yds":1,
    "Att":1,
    "TD":0,
    "20+":0,
    "40+":0,
    "Lng":1,
    "Rush 1st":1,
    "Rush 1st%":1.0,
    "Rush FUM":0
  },
  {
    "Player":"Kenny Stills",
    "Rush Yds":1,
    "Att":1,
    "TD":0,
    "20+":0,
    "40+":0,
    "Lng":1,
    "Rush 1st":0,
    "Rush 1st%":0.0,
    "Rush FUM":0
  },
  {
    "Player":"Michael Palardy",
    "Rush Yds":1,
    "Att":1,
    "TD":0,
    "20+":0,
    "40+":0,
    "Lng":1,
    "Rush 1st":0,
    "Rush 1st%":0.0,
    "Rush FUM":0
  },
  {
    "Player":"David Njoku",
    "Rush Yds":1,
    "Att":1,
    "TD":0,
    "20+":0,
    "40+":0,
    "Lng":1,
    "Rush 1st":0,
    "Rush 1st%":0.0,
    "Rush FUM":0
  },
  {
    "Player":"Dax Milne",
    "Rush Yds":1,
    "Att":1,
    "TD":0,
    "20+":0,
    "40+":0,
    "Lng":1,
    "Rush 1st":0,
    "Rush 1st%":0.0,
    "Rush FUM":0
  },
  {
    "Player":"Alec Ingold",
    "Rush Yds":1,
    "Att":2,
    "TD":0,
    "20+":0,
    "40+":0,
    "Lng":1,
    "Rush 1st":1,
    "Rush 1st%":2.0,
    "Rush FUM":0
  },
  {
    "Player":"Eric Ebron",
    "Rush Yds":1,
    "Att":1,
    "TD":1,
    "20+":0,
    "40+":0,
    "Lng":1,
    "Rush 1st":1,
    "Rush 1st%":1.0,
    "Rush FUM":0
  },
  {
    "Player":"Randall Cobb",
    "Rush Yds":1,
    "Att":1,
    "TD":0,
    "20+":0,
    "40+":0,
    "Lng":1,
    "Rush 1st":0,
    "Rush 1st%":0.0,
    "Rush FUM":0
  }
]