[
  {
    "Team":"49ers",
    "Avg":9.0,
    "Ret":25,
    "Yds":226,
    "PRet T":0,
    "20+":2,
    "40+":0,
    "Lng":"21",
    "FC":26,
    "FUM":3,
    "P Blk":0
  },
  {
    "Team":"Bears",
    "Avg":7.6,
    "Ret":25,
    "Yds":190,
    "PRet T":0,
    "20+":1,
    "40+":0,
    "Lng":"32",
    "FC":14,
    "FUM":3,
    "P Blk":0
  },
  {
    "Team":"Bengals",
    "Avg":10.1,
    "Ret":23,
    "Yds":232,
    "PRet T":0,
    "20+":3,
    "40+":0,
    "Lng":"29",
    "FC":20,
    "FUM":1,
    "P Blk":0
  },
  {
    "Team":"Bills",
    "Avg":11.9,
    "Ret":31,
    "Yds":370,
    "PRet T":1,
    "20+":5,
    "40+":1,
    "Lng":"84T",
    "FC":13,
    "FUM":2,
    "P Blk":0
  },
  {
    "Team":"Broncos",
    "Avg":13.4,
    "Ret":20,
    "Yds":267,
    "PRet T":1,
    "20+":3,
    "40+":2,
    "Lng":"83T",
    "FC":25,
    "FUM":3,
    "P Blk":0
  },
  {
    "Team":"Browns",
    "Avg":4.8,
    "Ret":24,
    "Yds":115,
    "PRet T":0,
    "20+":0,
    "40+":0,
    "Lng":"13",
    "FC":11,
    "FUM":0,
    "P Blk":0
  },
  {
    "Team":"Buccaneers",
    "Avg":5.9,
    "Ret":30,
    "Yds":176,
    "PRet T":0,
    "20+":1,
    "40+":0,
    "Lng":"21",
    "FC":14,
    "FUM":0,
    "P Blk":1
  },
  {
    "Team":"Cardinals",
    "Avg":5.4,
    "Ret":25,
    "Yds":136,
    "PRet T":0,
    "20+":2,
    "40+":0,
    "Lng":"24",
    "FC":15,
    "FUM":1,
    "P Blk":2
  },
  {
    "Team":"Chargers",
    "Avg":5.6,
    "Ret":18,
    "Yds":100,
    "PRet T":0,
    "20+":1,
    "40+":0,
    "Lng":"30",
    "FC":15,
    "FUM":1,
    "P Blk":0
  },
  {
    "Team":"Chiefs",
    "Avg":5.8,
    "Ret":28,
    "Yds":163,
    "PRet T":1,
    "20+":1,
    "40+":1,
    "Lng":"67T",
    "FC":15,
    "FUM":3,
    "P Blk":0
  },
  {
    "Team":"Colts",
    "Avg":10.1,
    "Ret":31,
    "Yds":312,
    "PRet T":0,
    "20+":3,
    "40+":0,
    "Lng":"26",
    "FC":15,
    "FUM":0,
    "P Blk":1
  },
  {
    "Team":"Cowboys",
    "Avg":9.1,
    "Ret":29,
    "Yds":265,
    "PRet T":0,
    "20+":4,
    "40+":1,
    "Lng":"73",
    "FC":14,
    "FUM":1,
    "P Blk":0
  },
  {
    "Team":"Dolphins",
    "Avg":11.1,
    "Ret":32,
    "Yds":354,
    "PRet T":1,
    "20+":3,
    "40+":1,
    "Lng":"88T",
    "FC":9,
    "FUM":3,
    "P Blk":1
  },
  {
    "Team":"Eagles",
    "Avg":8.8,
    "Ret":26,
    "Yds":230,
    "PRet T":1,
    "20+":2,
    "40+":1,
    "Lng":"73T",
    "FC":27,
    "FUM":3,
    "P Blk":0
  },
  {
    "Team":"Falcons",
    "Avg":8.9,
    "Ret":17,
    "Yds":152,
    "PRet T":0,
    "20+":2,
    "40+":0,
    "Lng":"24",
    "FC":23,
    "FUM":0,
    "P Blk":0
  },
  {
    "Team":"FootballTeam",
    "Avg":5.7,
    "Ret":31,
    "Yds":176,
    "PRet T":0,
    "20+":2,
    "40+":0,
    "Lng":"22",
    "FC":26,
    "FUM":7,
    "P Blk":0
  },
  {
    "Team":"Giants",
    "Avg":11.4,
    "Ret":20,
    "Yds":228,
    "PRet T":0,
    "20+":3,
    "40+":0,
    "Lng":"20",
    "FC":16,
    "FUM":0,
    "P Blk":0
  },
  {
    "Team":"Jaguars",
    "Avg":11.4,
    "Ret":18,
    "Yds":205,
    "PRet T":1,
    "20+":1,
    "40+":1,
    "Lng":"91T",
    "FC":12,
    "FUM":1,
    "P Blk":1
  },
  {
    "Team":"Jets",
    "Avg":8.6,
    "Ret":10,
    "Yds":86,
    "PRet T":0,
    "20+":0,
    "40+":0,
    "Lng":"18",
    "FC":29,
    "FUM":0,
    "P Blk":2
  },
  {
    "Team":"Lions",
    "Avg":12.8,
    "Ret":17,
    "Yds":217,
    "PRet T":1,
    "20+":2,
    "40+":1,
    "Lng":"74T",
    "FC":17,
    "FUM":2,
    "P Blk":3
  },
  {
    "Team":"Packers",
    "Avg":4.8,
    "Ret":11,
    "Yds":53,
    "PRet T":0,
    "20+":0,
    "40+":0,
    "Lng":"11",
    "FC":19,
    "FUM":1,
    "P Blk":0
  },
  {
    "Team":"Panthers",
    "Avg":5.9,
    "Ret":20,
    "Yds":117,
    "PRet T":0,
    "20+":1,
    "40+":0,
    "Lng":"20",
    "FC":18,
    "FUM":1,
    "P Blk":0
  },
  {
    "Team":"Patriots",
    "Avg":15.5,
    "Ret":23,
    "Yds":357,
    "PRet T":1,
    "20+":4,
    "40+":3,
    "Lng":"70T",
    "FC":16,
    "FUM":1,
    "P Blk":0
  },
  {
    "Team":"Raiders",
    "Avg":11.5,
    "Ret":23,
    "Yds":265,
    "PRet T":0,
    "20+":3,
    "40+":0,
    "Lng":"32",
    "FC":10,
    "FUM":1,
    "P Blk":0
  },
  {
    "Team":"Rams",
    "Avg":6.9,
    "Ret":34,
    "Yds":235,
    "PRet T":0,
    "20+":1,
    "40+":0,
    "Lng":"34",
    "FC":28,
    "FUM":4,
    "P Blk":0
  },
  {
    "Team":"Ravens",
    "Avg":9.0,
    "Ret":27,
    "Yds":244,
    "PRet T":0,
    "20+":1,
    "40+":0,
    "Lng":"20",
    "FC":18,
    "FUM":0,
    "P Blk":0
  },
  {
    "Team":"Saints",
    "Avg":10.2,
    "Ret":39,
    "Yds":399,
    "PRet T":0,
    "20+":2,
    "40+":1,
    "Lng":"42",
    "FC":18,
    "FUM":2,
    "P Blk":0
  },
  {
    "Team":"Seahawks",
    "Avg":8.6,
    "Ret":22,
    "Yds":189,
    "PRet T":0,
    "20+":1,
    "40+":0,
    "Lng":"20",
    "FC":22,
    "FUM":2,
    "P Blk":1
  },
  {
    "Team":"Steelers",
    "Avg":9.6,
    "Ret":37,
    "Yds":356,
    "PRet T":0,
    "20+":2,
    "40+":2,
    "Lng":"57",
    "FC":22,
    "FUM":3,
    "P Blk":0
  },
  {
    "Team":"Texans",
    "Avg":7.9,
    "Ret":20,
    "Yds":158,
    "PRet T":0,
    "20+":0,
    "40+":0,
    "Lng":"19",
    "FC":11,
    "FUM":2,
    "P Blk":1
  },
  {
    "Team":"Titans",
    "Avg":9.0,
    "Ret":23,
    "Yds":208,
    "PRet T":0,
    "20+":2,
    "40+":1,
    "Lng":"40",
    "FC":12,
    "FUM":0,
    "P Blk":0
  },
  {
    "Team":"Vikings",
    "Avg":4.3,
    "Ret":16,
    "Yds":69,
    "PRet T":0,
    "20+":0,
    "40+":0,
    "Lng":"13",
    "FC":11,
    "FUM":4,
    "P Blk":0
  }
]